<?xml version="1.0" encoding="utf-8"?>
<resources xmlns:tools="http://schemas.android.com/tools" tools:ignore="MissingTranslation">
    <bool name="current_gtfs_rts_schedule_available">true</bool>
    <bool name="current_gtfs_rts_frequency_available">false</bool>
    <string name="current_gtfs_rts_area_min_lat">52.204934</string>
    <string name="current_gtfs_rts_area_max_lat">52.315697</string>
    <string name="current_gtfs_rts_area_min_lng">-113.859632</string>
    <string name="current_gtfs_rts_area_max_lng">-113.746221</string>
    <integer name="current_gtfs_rts_first_departure_in_sec">1707057900</integer><!-- 2024/02/04 07:45:00 MST -->
    <integer name="current_gtfs_rts_last_departure_in_sec">1713074040</integer><!-- 2024/04/13 23:54:00 MDT -->
</resources>
